[{
    "kind": "youtube#searchListResponse",
    "etag": "3HE0PBm0jG-alaSQ6H5StvyRhRI",
    "nextPageToken": "CAUQAA",
    "regionCode": "IN",
    "pageInfo": {
    "totalResults": 1000000,
    "resultsPerPage": 5
    },
    "items": [
    {
    "kind": "youtube#searchResult",
    "etag": "wkI-McDFCjsHrL2-B7UyvdDwQB8",
    "id": {
    "kind": "youtube#video",
    "videoId": "1MzgFvzubug"
    },
    "snippet": {
    "publishedAt": "2024-03-12T13:38:45Z",
    "channelId": "UCY0f6XgwdlmOL1oV-wJ-DfA",
    "title": "Top Christian Worship Songs 2023 ✝️ Playlist Hillsong Praise &amp; Worship Songs 🙏 Praise Worship Music",
    "description": "Thanks everyone who watching this video. I had redirected this video live stream to another video as link ...",
    "thumbnails": {
    "default": {
    "url": "https://i.ytimg.com/vi/1MzgFvzubug/default_live.jpg",
    "width": 120,
    "height": 90
    },
    "medium": {
    "url": "https://i.ytimg.com/vi/1MzgFvzubug/mqdefault_live.jpg",
    "width": 320,
    "height": 180
    },
    "high": {
    "url": "https://i.ytimg.com/vi/1MzgFvzubug/hqdefault_live.jpg",
    "width": 480,
    "height": 360
    }
    },
    "channelTitle": "Praise Worship Music",
    "liveBroadcastContent": "live",
    "publishTime": "2024-03-12T13:38:45Z"
    }
    },
    {
    "kind": "youtube#searchResult",
    "etag": "dqwIgychri6F3gs8AGsQKMA6JbM",
    "id": {
    "kind": "youtube#video",
    "videoId": "x0faUGSzpJ0"
    },
    "snippet": {
    "publishedAt": "2024-03-12T17:03:18Z",
    "channelId": "UCKvKjZ3l9azWz4F49q2R3tQ",
    "title": "Stress Relief with Relaxing Jazz Instrumental Music ☕ Warm Jazz Music at Cozy Coffee Shop Ambience",
    "description": "Stress Relief with Relaxing Jazz Instrumental Music ☕ Warm Jazz Music at Cozy Coffee Shop Ambience Hello, my friend!",
    "thumbnails": {
    "default": {
    "url": "https://i.ytimg.com/vi/x0faUGSzpJ0/default_live.jpg",
    "width": 120,
    "height": 90
    },
    "medium": {
    "url": "https://i.ytimg.com/vi/x0faUGSzpJ0/mqdefault_live.jpg",
    "width": 320,
    "height": 180
    },
    "high": {
    "url": "https://i.ytimg.com/vi/x0faUGSzpJ0/hqdefault_live.jpg",
    "width": 480,
    "height": 360
    }
    },
    "channelTitle": "Coffee Relaxing Jazz",
    "liveBroadcastContent": "live",
    "publishTime": "2024-03-12T17:03:18Z"
    }
    },
    {
    "kind": "youtube#searchResult",
    "etag": "iqRhxDP42pHXFcH0AtkCTNWJey0",
    "id": {
    "kind": "youtube#video",
    "videoId": "a9gTLNuw8tQ"
    },
    "snippet": {
    "publishedAt": "2024-03-10T01:03:48Z",
    "channelId": "UC4zvcd2F0UebXfG4LfygTmQ",
    "title": "Old Vs New Bollywood Mashup 2024 | Superhits Romantic Hindi Songs Mashup Live - DJ MaShUP 2024",
    "description": "Old Vs New Bollywood Mashup 2024 | Superhits Romantic Hindi Songs Mashup Live - DJ MaShUP 2024 ...",
    "thumbnails": {
    "default": {
    "url": "https://i.ytimg.com/vi/a9gTLNuw8tQ/default_live.jpg",
    "width": 120,
    "height": 90
    },
    "medium": {
    "url": "https://i.ytimg.com/vi/a9gTLNuw8tQ/mqdefault_live.jpg",
    "width": 320,
    "height": 180
    },
    "high": {
    "url": "https://i.ytimg.com/vi/a9gTLNuw8tQ/hqdefault_live.jpg",
    "width": 480,
    "height": 360
    }
    },
    "channelTitle": "New Hindi PartyMix",
    "liveBroadcastContent": "live",
    "publishTime": "2024-03-10T01:03:48Z"
    }
    },
    {
    "kind": "youtube#searchResult",
    "etag": "v_6TnHFFSpLwdsWDS9myYTxXh18",
    "id": {
    "kind": "youtube#video",
    "videoId": "HIbJ2q0ZtJg"
    },
    "snippet": {
    "publishedAt": "2024-03-11T21:15:00Z",
    "channelId": "UCwKAkgOJ7TISGlwZAq1H0Vg",
    "title": "Best Romantic Love Songs 80s 90s - Best Love Songs Medley  -  Old Love Song Sweet Memories",
    "description": "Best Romantic Love Songs 80s 90s - Best Love Songs Medley - Old Love Song Sweet Memories Best Romantic Love Songs 80s ...",
    "thumbnails": {
    "default": {
    "url": "https://i.ytimg.com/vi/HIbJ2q0ZtJg/default.jpg",
    "width": 120,
    "height": 90
    },
    "medium": {
    "url": "https://i.ytimg.com/vi/HIbJ2q0ZtJg/mqdefault.jpg",
    "width": 320,
    "height": 180
    },
    "high": {
    "url": "https://i.ytimg.com/vi/HIbJ2q0ZtJg/hqdefault.jpg",
    "width": 480,
    "height": 360
    }
    },
    "channelTitle": "Romantic Melodies",
    "liveBroadcastContent": "none",
    "publishTime": "2024-03-11T21:15:00Z"
    }
    },
    {
    "kind": "youtube#searchResult",
    "etag": "G_fJyRf_eBg5IjJyRABHbekXiVg",
    "id": {
    "kind": "youtube#video",
    "videoId": "KIk20JaidTs"
    },
    "snippet": {
    "publishedAt": "2024-03-12T07:26:43Z",
    "channelId": "UCwobzUc3z-0PrFpoRxNszXQ",
    "title": "🔴 Relaxing Zen Music 24/7, Stress Relief Music, Sleep Music, Meditation Music, Study, Calming Music",
    "description": "Enjoy our latest relaxing music live stream: youtube.com/yellowbrickcinema/live Relaxing Zen Music 24/7, Stress Relief Music, ...",
    "thumbnails": {
    "default": {
    "url": "https://i.ytimg.com/vi/KIk20JaidTs/default_live.jpg",
    "width": 120,
    "height": 90
    },
    "medium": {
    "url": "https://i.ytimg.com/vi/KIk20JaidTs/mqdefault_live.jpg",
    "width": 320,
    "height": 180
    },
    "high": {
    "url": "https://i.ytimg.com/vi/KIk20JaidTs/hqdefault_live.jpg",
    "width": 480,
    "height": 360
    }
    },
    "channelTitle": "Yellow Brick Cinema - Relaxing Music",
    "liveBroadcastContent": "live",
    "publishTime": "2024-03-12T07:26:43Z"
    }
    }
    ]
    }]